docmesh_core/__init__.py
docmesh_core/cos/__init__.py
docmesh_core/cos/figure.py
docmesh_core/db/__init__.py
docmesh_core/db/auth.py
docmesh_core/db/figure.py
docmesh_core/db/message.py
docmesh_core/db/poster.py
docmesh_core/db/neo/__init__.py
docmesh_core/db/neo/base.py
docmesh_core/db/neo/collection.py
docmesh_core/db/neo/common.py
docmesh_core/db/neo/entity.py
docmesh_core/db/neo/graph.py
docmesh_core/db/neo/paper.py
docmesh_core/db/neo/recommend.py
docmesh_core/db/neo/utils.py
docmesh_core/db/neo/venue.py
docmesh_core/utils/__init__.py
docmesh_core/utils/figure_extraction.py
docmesh_core/utils/semantic_scholar.py
docmesh_core-0.0.20.dist-info/WHEEL
docmesh_core-0.0.20.dist-info/METADATA
docmesh_core-0.0.20.dist-info/RECORD
